{
  "status_label": "IPCDB_SUCCESS",
  "responce": {
    "id": 308,
    "token_id": 308,
    "name": "",
    "attribute_seed": "0x58edf0149eb80b2cb8729b62e65f70200b3b351faf96dce1fd29146c6746987f",
    "dna": "0x442cf7810f19687cce94f4072369753dc2960f7eb691e0bb278a8f0a90358c1a",
    "birth": 1522790477,
    "price": "10000",
    "gold": 0,
    "xp": 0,
    "owner": "0xca77824C795854fC00E5F43721eE8322B5F4A6A5",
    "race": 2,
    "subrace": 8,
    "gender": 2,
    "height": 69,
    "eye_color": 3,
    "hair_color": 33,
    "skin_color": 7,
    "handedness": 1,
    "strength": 15,
    "force": 3,
    "sustain": 6,
    "tolerance": 6,
    "dexterity": 10,
    "speed": 1,
    "precision": 4,
    "reaction": 5,
    "intelligence": 8,
    "memory": 1,
    "processing": 2,
    "reasoning": 5,
    "constitution": 10,
    "healing": 3,
    "fortitude": 4,
    "vitality": 3,
    "luck": 11,
    "accessories": 0,
    "last_updated": 1657894877,
    "meta": {
      "sprite": "308",
      "card": 308,
      "canon": "",
      "rumor": ""
    }
  }
}