{
  "status_label": "IPCDB_SUCCESS",
  "responce": {
    "id": 560,
    "token_id": 560,
    "name": "Tressic Nalaposh",
    "attribute_seed": "0x8f21cf87c54d19b0ef7f8d2353bac4fade16ba25491b576d58cd4a9294457072",
    "dna": "0x2d693ac9b671897283feb784fa919f1f96fe1cd45681b207b0a8a36c43ed2896",
    "birth": 1533768173,
    "price": "1000000",
    "gold": 0,
    "xp": 0,
    "owner": "0x0A6c3Df4dA90879b3426a3A90ff45a128D17DF6E",
    "race": 1,
    "subrace": 2,
    "gender": 1,
    "height": 74,
    "eye_color": 19,
    "hair_color": 12,
    "skin_color": 8,
    "handedness": 2,
    "strength": 10,
    "force": 4,
    "sustain": 1,
    "tolerance": 5,
    "dexterity": 11,
    "speed": 4,
    "precision": 5,
    "reaction": 2,
    "intelligence": 12,
    "memory": 1,
    "processing": 5,
    "reasoning": 6,
    "constitution": 8,
    "healing": 3,
    "fortitude": 4,
    "vitality": 1,
    "luck": 11,
    "accessories": 0,
    "last_updated": 1657895509,
    "meta": {
      "sprite": "560",
      "card": 560,
      "canon": "",
      "rumor": ""
    }
  }
}