{
  "status_label": "IPCDB_SUCCESS",
  "responce": {
    "id": 855,
    "token_id": 855,
    "name": "Khula",
    "attribute_seed": "0xe5304bf66419a8bfa9f97354bf7f9881488bc137379098e77182a2ec90a18e70",
    "dna": "0x12849f936aba6448f9c4ea3c3214ff28d46bdc17091a05aa190d4df1f5b2ee26",
    "birth": 1539285758,
    "price": "100000000",
    "gold": 0,
    "xp": 0,
    "owner": "0x15F7320adb990020956D29Edb6ba17f3D468001e",
    "race": 1,
    "subrace": 3,
    "gender": 2,
    "height": 75,
    "eye_color": 19,
    "hair_color": 12,
    "skin_color": 10,
    "handedness": 2,
    "strength": 10,
    "force": 6,
    "sustain": 2,
    "tolerance": 2,
    "dexterity": 10,
    "speed": 6,
    "precision": 3,
    "reaction": 1,
    "intelligence": 13,
    "memory": 4,
    "processing": 5,
    "reasoning": 4,
    "constitution": 11,
    "healing": 6,
    "fortitude": 3,
    "vitality": 2,
    "luck": 10,
    "accessories": 0,
    "last_updated": 1657895799,
    "meta": {
      "sprite": "855",
      "card": 855,
      "canon": "",
      "rumor": ""
    }
  }
}