{
  "status_label": "IPCDB_SUCCESS",
  "responce": {
    "id": 931,
    "token_id": 931,
    "name": "Nertomaros",
    "attribute_seed": "0x7b419e24dbbee890d41619eae990d6349a1f5d5c88c70566246a554027de159d",
    "dna": "0xe21259115f17c34189acec04b392a41920e07c47371049d3462573a9b59a9ce2",
    "birth": 1539298183,
    "price": "100000000",
    "gold": 0,
    "xp": 0,
    "owner": "0xF9645DEe4EdCa70888bC862A9f61D642193663F3",
    "race": 4,
    "subrace": 19,
    "gender": 2,
    "height": 75,
    "eye_color": 26,
    "hair_color": 17,
    "skin_color": 17,
    "handedness": 2,
    "strength": 9,
    "force": 3,
    "sustain": 2,
    "tolerance": 4,
    "dexterity": 12,
    "speed": 1,
    "precision": 6,
    "reaction": 5,
    "intelligence": 15,
    "memory": 6,
    "processing": 4,
    "reasoning": 5,
    "constitution": 8,
    "healing": 1,
    "fortitude": 1,
    "vitality": 6,
    "luck": 10,
    "accessories": 0,
    "last_updated": 1657895873,
    "meta": {
      "sprite": "931",
      "card": 931,
      "canon": "",
      "rumor": ""
    }
  }
}