{
  "status_label": "IPCDB_SUCCESS",
  "responce": {
    "id": 1196,
    "token_id": 1196,
    "name": "Karson Stanley",
    "attribute_seed": "0xdcaf0274e3b6c04c361c759d8053b842cdf36c3e5e54d33df57fb0d89654551c",
    "dna": "0x4e6f4f41f34ac696effb639b64c7e65759389450cc432a94f493bfb17a1ce73e",
    "birth": 1539649943,
    "price": "100000000",
    "gold": 0,
    "xp": 0,
    "owner": "0xc61f077726B51DCF307C05Ab4b9dbc454F072A80",
    "race": 2,
    "subrace": 9,
    "gender": 1,
    "height": 64,
    "eye_color": 12,
    "hair_color": 17,
    "skin_color": 7,
    "handedness": 2,
    "strength": 12,
    "force": 6,
    "sustain": 5,
    "tolerance": 1,
    "dexterity": 14,
    "speed": 3,
    "precision": 6,
    "reaction": 5,
    "intelligence": 9,
    "memory": 5,
    "processing": 2,
    "reasoning": 2,
    "constitution": 8,
    "healing": 1,
    "fortitude": 3,
    "vitality": 4,
    "luck": 11,
    "accessories": 0,
    "last_updated": 1657896260,
    "meta": {
      "sprite": "1196",
      "card": 1196,
      "canon": "",
      "rumor": ""
    }
  }
}