{
  "status_label": "IPCDB_SUCCESS",
  "responce": {
    "id": 1628,
    "token_id": 1628,
    "name": "Sarvar",
    "attribute_seed": "0xe13cb01b8cbecb4d2a8bbabcc9abf70d08d34ebd77a6c512d7d9a4a260cd1b9f",
    "dna": "0x3c80ab760ed1d2a3e694667ede5778ce5a7d051c9d6bef5473dd21dc304ab0c4",
    "birth": 1540859317,
    "price": "10000",
    "gold": 0,
    "xp": 0,
    "owner": "0x82DfBC447EE0708db29b3235E6D243876C8f9DBf",
    "race": 2,
    "subrace": 9,
    "gender": 2,
    "height": 69,
    "eye_color": 12,
    "hair_color": 17,
    "skin_color": 10,
    "handedness": 1,
    "strength": 13,
    "force": 6,
    "sustain": 2,
    "tolerance": 5,
    "dexterity": 10,
    "speed": 1,
    "precision": 4,
    "reaction": 5,
    "intelligence": 8,
    "memory": 5,
    "processing": 2,
    "reasoning": 1,
    "constitution": 14,
    "healing": 4,
    "fortitude": 5,
    "vitality": 5,
    "luck": 10,
    "accessories": 0,
    "last_updated": 1657897049,
    "meta": {
      "sprite": "1628",
      "card": 1628,
      "canon": "",
      "rumor": ""
    }
  }
}