{
  "status_label": "IPCDB_SUCCESS",
  "responce": {
    "id": 2181,
    "token_id": 2181,
    "name": "Arel Valdithas",
    "attribute_seed": "0x04f77a5f177567536c72986f1ce8ca8a8899a605b4c02e68421baa02b3d39556",
    "dna": "0x306a86c568ee00b8ee276dc9aef45621f89ba1254261187e568959c75351a63c",
    "birth": 1542142038,
    "price": "10000",
    "gold": 0,
    "xp": 0,
    "owner": "0x22Ff5C207333d2D4Fcd2Abe76283739830588664",
    "race": 1,
    "subrace": 2,
    "gender": 2,
    "height": 76,
    "eye_color": 25,
    "hair_color": 11,
    "skin_color": 9,
    "handedness": 2,
    "strength": 10,
    "force": 1,
    "sustain": 6,
    "tolerance": 3,
    "dexterity": 7,
    "speed": 3,
    "precision": 1,
    "reaction": 3,
    "intelligence": 8,
    "memory": 3,
    "processing": 2,
    "reasoning": 3,
    "constitution": 10,
    "healing": 3,
    "fortitude": 4,
    "vitality": 3,
    "luck": 13,
    "accessories": 0,
    "last_updated": 1657897595,
    "meta": {
      "sprite": "2181",
      "card": 2181,
      "canon": "",
      "rumor": ""
    }
  }
}