{
  "status_label": "IPCDB_SUCCESS",
  "responce": {
    "id": 2673,
    "token_id": 2673,
    "name": "Ammi",
    "attribute_seed": "0xcac7aeb555416889f2ddaf883787cf4d140fc78dce481106286a3e4a1b3629a9",
    "dna": "0xd65d4a13e375807501dc3e6cb2e5cc02c616474b461165e47d196287628f1300",
    "birth": 1561504103,
    "price": "10000",
    "gold": 0,
    "xp": 0,
    "owner": "0x51D4791544C7d90D354e92A3a4C2ea3DaEcfdb36",
    "race": 4,
    "subrace": 21,
    "gender": 2,
    "height": 75,
    "eye_color": 12,
    "hair_color": 12,
    "skin_color": 19,
    "handedness": 2,
    "strength": 15,
    "force": 5,
    "sustain": 5,
    "tolerance": 5,
    "dexterity": 9,
    "speed": 5,
    "precision": 2,
    "reaction": 2,
    "intelligence": 13,
    "memory": 3,
    "processing": 4,
    "reasoning": 6,
    "constitution": 15,
    "healing": 6,
    "fortitude": 5,
    "vitality": 4,
    "luck": 8,
    "accessories": 0,
    "last_updated": 1657898082,
    "meta": {
      "sprite": "2673",
      "card": 2673,
      "canon": "",
      "rumor": ""
    }
  }
}