{
  "status_label": "IPCDB_SUCCESS",
  "responce": {
    "id": 2868,
    "token_id": 2887,
    "name": "mfer",
    "attribute_seed": "0x31136f4fee94d1d946140d4e20ea4d3680f52937ee91ea4f151e136fc387b14f",
    "dna": "0xc976306228f39e53b7bef3425b7f2750707522c9eebbe5ae8d3e24b57835216f",
    "birth": 1657058568,
    "price": "300000",
    "gold": 0,
    "xp": 0,
    "owner": "0xDd69c8B49873D6b9Bf0E4fd90A5bfCb819Cc2456",
    "race": 4,
    "subrace": 21,
    "gender": 1,
    "height": 74,
    "eye_color": 26,
    "hair_color": 12,
    "skin_color": 20,
    "handedness": 2,
    "strength": 6,
    "force": 2,
    "sustain": 1,
    "tolerance": 3,
    "dexterity": 12,
    "speed": 2,
    "precision": 6,
    "reaction": 4,
    "intelligence": 13,
    "memory": 5,
    "processing": 6,
    "reasoning": 2,
    "constitution": 4,
    "healing": 1,
    "fortitude": 1,
    "vitality": 2,
    "luck": 13,
    "accessories": 0,
    "last_updated": 1657898295,
    "meta": {
      "sprite": 2887,
      "card": 2887,
      "canon": "",
      "rumor": ""
    }
  }
}