{
  "status_label": "IPCDB_SUCCESS",
  "responce": {
    "id": 4143,
    "token_id": 3141,
    "name": "Tigger",
    "attribute_seed": "0xb532738052c24d784b4f11a04aae4b5121e0680feced7c1eda4641b4e54801b1",
    "dna": "0xa633020bf56df3a5fb96630a3346362d3aa5a01a9d416e713a44be6c8e185789",
    "birth": 1657063220,
    "price": "100000",
    "gold": 0,
    "xp": 0,
    "owner": "0x5e867FFb48C0a743bAb214748002c63cB0A23426",
    "race": 3,
    "subrace": 14,
    "gender": 1,
    "height": 46,
    "eye_color": 19,
    "hair_color": 17,
    "skin_color": 8,
    "handedness": 2,
    "strength": 10,
    "force": 5,
    "sustain": 2,
    "tolerance": 3,
    "dexterity": 11,
    "speed": 4,
    "precision": 2,
    "reaction": 5,
    "intelligence": 7,
    "memory": 2,
    "processing": 3,
    "reasoning": 2,
    "constitution": 7,
    "healing": 2,
    "fortitude": 1,
    "vitality": 4,
    "luck": 13,
    "accessories": 0,
    "last_updated": 1657898547,
    "meta": {
      "sprite": 3141,
      "card": 3141,
      "canon": "",
      "rumor": ""
    }
  }
}