{
  "status_label": "IPCDB_SUCCESS",
  "responce": {
    "id": 4747,
    "token_id": 3820,
    "name": "Vee",
    "attribute_seed": "0xedf61be6978946ee6441002845d292fce2be13e8e2957f96ee9fb1541cf5c667",
    "dna": "0x92a382664f84811a8cc3442e423539653edab5b0aa05f11e08f1d5b71bd19a11",
    "birth": 1657067067,
    "price": "100000000",
    "gold": 0,
    "xp": 0,
    "owner": "0x42edE40cD8B423d8Bcb3CF4A7F2b4EB66527183f",
    "race": 3,
    "subrace": 14,
    "gender": 2,
    "height": 51,
    "eye_color": 3,
    "hair_color": 13,
    "skin_color": 8,
    "handedness": 2,
    "strength": 13,
    "force": 6,
    "sustain": 6,
    "tolerance": 1,
    "dexterity": 14,
    "speed": 6,
    "precision": 4,
    "reaction": 4,
    "intelligence": 11,
    "memory": 2,
    "processing": 6,
    "reasoning": 3,
    "constitution": 4,
    "healing": 2,
    "fortitude": 1,
    "vitality": 1,
    "luck": 11,
    "accessories": 0,
    "last_updated": 1657899220,
    "meta": {
      "sprite": 3820,
      "card": 3820,
      "canon": "",
      "rumor": ""
    }
  }
}