{
  "status_label": "IPCDB_SUCCESS",
  "responce": {
    "id": 5255,
    "token_id": 4357,
    "name": "Lucky",
    "attribute_seed": "0x1776e7c83f6d1010276b7051db974c1bd70c6b30fe74bc9713fad84efb5d6271",
    "dna": "0x5493bcdc5a14f922de9c64fe91e3e6f88040e45769c79102d337e9a0807115fd",
    "birth": 1657067481,
    "price": "500000",
    "gold": 0,
    "xp": 0,
    "owner": "0x013026c99250694e2Cd6C37793771f2a7b2618a2",
    "race": 2,
    "subrace": 10,
    "gender": 2,
    "height": 73,
    "eye_color": 3,
    "hair_color": 17,
    "skin_color": 8,
    "handedness": 2,
    "strength": 10,
    "force": 1,
    "sustain": 3,
    "tolerance": 6,
    "dexterity": 10,
    "speed": 5,
    "precision": 2,
    "reaction": 3,
    "intelligence": 3,
    "memory": 1,
    "processing": 1,
    "reasoning": 1,
    "constitution": 8,
    "healing": 3,
    "fortitude": 3,
    "vitality": 2,
    "luck": 14,
    "accessories": 0,
    "last_updated": 1657899751,
    "meta": {
      "sprite": 4357,
      "card": 4357,
      "canon": "",
      "rumor": ""
    }
  }
}