{
  "status_label": "IPCDB_SUCCESS",
  "responce": {
    "id": 5591,
    "token_id": 4713,
    "name": "Lucky",
    "attribute_seed": "0x285ef69627afd8ba7948ff079bf2c65928edd9014c247361611a658fdb0ad40e",
    "dna": "0xc31ef1895230f08816bbfe2f5288ba5dc83d0ea66312477e0961e871c640aaf4",
    "birth": 1657067593,
    "price": "500000",
    "gold": 0,
    "xp": 0,
    "owner": "0xcc288CAA63B8EA8C551fD45368Ea5dA21c831cD6",
    "race": 3,
    "subrace": 13,
    "gender": 2,
    "height": 51,
    "eye_color": 12,
    "hair_color": 12,
    "skin_color": 0,
    "handedness": 2,
    "strength": 10,
    "force": 1,
    "sustain": 3,
    "tolerance": 6,
    "dexterity": 10,
    "speed": 4,
    "precision": 1,
    "reaction": 5,
    "intelligence": 14,
    "memory": 6,
    "processing": 5,
    "reasoning": 3,
    "constitution": 9,
    "healing": 2,
    "fortitude": 6,
    "vitality": 1,
    "luck": 11,
    "accessories": 0,
    "last_updated": 1657900226,
    "meta": {
      "sprite": 4713,
      "card": 4713,
      "canon": "",
      "rumor": ""
    }
  }
}