{
  "status_label": "IPCDB_SUCCESS",
  "responce": {
    "id": 5740,
    "token_id": 4863,
    "name": "Lucky",
    "attribute_seed": "0x683de3ce216d027b3f1ecceb221eccd704f00d0fd2f176f71edcaac920187159",
    "dna": "0x01c5c5550284c9f358a8dcb708eafc0b4b9292511c71006065a7ee49ece1c2a0",
    "birth": 1657067650,
    "price": "500000",
    "gold": 0,
    "xp": 0,
    "owner": "0x013026c99250694e2Cd6C37793771f2a7b2618a2",
    "race": 1,
    "subrace": 3,
    "gender": 2,
    "height": 74,
    "eye_color": 24,
    "hair_color": 17,
    "skin_color": 8,
    "handedness": 1,
    "strength": 11,
    "force": 3,
    "sustain": 2,
    "tolerance": 6,
    "dexterity": 9,
    "speed": 5,
    "precision": 1,
    "reaction": 3,
    "intelligence": 6,
    "memory": 1,
    "processing": 3,
    "reasoning": 2,
    "constitution": 12,
    "healing": 1,
    "fortitude": 5,
    "vitality": 6,
    "luck": 12,
    "accessories": 0,
    "last_updated": 1657900382,
    "meta": {
      "sprite": 4863,
      "card": 4863,
      "canon": "",
      "rumor": ""
    }
  }
}