{
  "status_label": "IPCDB_SUCCESS",
  "responce": {
    "id": 6121,
    "token_id": 5295,
    "name": "Lucky",
    "attribute_seed": "0xd9faed6eb391123a22253d740c6f43665415e6b123d70a4378261456610907ad",
    "dna": "0x25ed3ee32ef377ea46b400c9009bb9dce7df1b194f891ff325a0cc3e48d2846b",
    "birth": 1657067914,
    "price": "500000",
    "gold": 0,
    "xp": 0,
    "owner": "0xf1eC6452A99cBb6AbC642B19a462C149621C38B9",
    "race": 1,
    "subrace": 4,
    "gender": 1,
    "height": 74,
    "eye_color": 26,
    "hair_color": 15,
    "skin_color": 12,
    "handedness": 2,
    "strength": 18,
    "force": 6,
    "sustain": 6,
    "tolerance": 6,
    "dexterity": 12,
    "speed": 3,
    "precision": 5,
    "reaction": 4,
    "intelligence": 4,
    "memory": 1,
    "processing": 2,
    "reasoning": 1,
    "constitution": 6,
    "healing": 1,
    "fortitude": 2,
    "vitality": 3,
    "luck": 11,
    "accessories": 0,
    "last_updated": 1657900815,
    "meta": {
      "sprite": 5295,
      "card": 5295,
      "canon": "",
      "rumor": ""
    }
  }
}