{
  "status_label": "IPCDB_SUCCESS",
  "responce": {
    "id": 3209,
    "token_id": 7682,
    "name": "Lucky",
    "attribute_seed": "0x4ba2d33520bf2cb723fea3c5844e6a597f11c6121ca60a33d0f6cd7d4eb2273c",
    "dna": "0x029d5265fd6773b074968507fc0331de6ddbbaf0afd55930f06dbb1e74adf1ed",
    "birth": 1657068891,
    "price": "500000",
    "gold": 0,
    "xp": 0,
    "owner": "0x97DA20Dc2BD46174dA79D71a385B7248527fbEE6",
    "race": 1,
    "subrace": 3,
    "gender": 1,
    "height": 73,
    "eye_color": 24,
    "hair_color": 12,
    "skin_color": 8,
    "handedness": 2,
    "strength": 11,
    "force": 2,
    "sustain": 4,
    "tolerance": 5,
    "dexterity": 8,
    "speed": 2,
    "precision": 1,
    "reaction": 5,
    "intelligence": 8,
    "memory": 2,
    "processing": 5,
    "reasoning": 1,
    "constitution": 15,
    "healing": 6,
    "fortitude": 4,
    "vitality": 5,
    "luck": 11,
    "accessories": 0,
    "last_updated": 1657903424,
    "meta": {
      "sprite": 7682,
      "card": 7682,
      "canon": "",
      "rumor": ""
    }
  }
}