{
  "status_label": "IPCDB_SUCCESS",
  "responce": {
    "id": 8816,
    "token_id": 8231,
    "name": "stevethepirate",
    "attribute_seed": "0xdf56830fac2cde4d02fb1770b2a19cc9c9f378471f1d592d7ce7da4f701d3f0f",
    "dna": "0xa2066e8a40d52b031eb790e4894c7e918e18f395c7927e052aeabdbd7135991e",
    "birth": 1657069209,
    "price": "100000000",
    "gold": 0,
    "xp": 0,
    "owner": "0xCB57E66Ce71582729a78d3327f5966CEBAd23ec6",
    "race": 3,
    "subrace": 13,
    "gender": 2,
    "height": 51,
    "eye_color": 27,
    "hair_color": 33,
    "skin_color": 37,
    "handedness": 2,
    "strength": 13,
    "force": 6,
    "sustain": 3,
    "tolerance": 4,
    "dexterity": 8,
    "speed": 1,
    "precision": 5,
    "reaction": 2,
    "intelligence": 9,
    "memory": 6,
    "processing": 2,
    "reasoning": 1,
    "constitution": 10,
    "healing": 6,
    "fortitude": 1,
    "vitality": 3,
    "luck": 11,
    "accessories": 0,
    "last_updated": 1657903967,
    "meta": {
      "sprite": 8231,
      "card": 8231,
      "canon": "",
      "rumor": ""
    }
  }
}