{
  "status_label": "IPCDB_SUCCESS",
  "responce": {
    "id": 3272,
    "token_id": 8378,
    "name": "kaboum",
    "attribute_seed": "0x594913cda2ea78569c8f0d64f465d80f9270b652a6bfd5c2901144701db1cacb",
    "dna": "0x60575a294dfd9c0bba8d5d25ee95de367430c37b9af77a242782f683a4f35065",
    "birth": 1657069315,
    "price": "200000",
    "gold": 0,
    "xp": 0,
    "owner": "0xF0F5Dafa46E64940855311e97348Dd013980A496",
    "race": 2,
    "subrace": 8,
    "gender": 1,
    "height": 63,
    "eye_color": 6,
    "hair_color": 11,
    "skin_color": 8,
    "handedness": 2,
    "strength": 6,
    "force": 3,
    "sustain": 2,
    "tolerance": 1,
    "dexterity": 15,
    "speed": 5,
    "precision": 4,
    "reaction": 6,
    "intelligence": 10,
    "memory": 3,
    "processing": 3,
    "reasoning": 4,
    "constitution": 8,
    "healing": 4,
    "fortitude": 1,
    "vitality": 3,
    "luck": 12,
    "accessories": 0,
    "last_updated": 1657904113,
    "meta": {
      "sprite": 8378,
      "card": 8378,
      "canon": "",
      "rumor": ""
    }
  }
}