{
  "status_label": "IPCDB_SUCCESS",
  "responce": {
    "id": 8935,
    "token_id": 8381,
    "name": "Lucky",
    "attribute_seed": "0xa94f15daf85fb821cffbe30a1450a65088a784a825694fb977e72bd25bb32383",
    "dna": "0xd5496eba4f72bc141f7423778b6485f540f946c8da2a7482e2b56858486e949e",
    "birth": 1657069315,
    "price": "500000",
    "gold": 0,
    "xp": 0,
    "owner": "0x29f1327bb1d97c50aC4B62d7686DE154D40d207a",
    "race": 4,
    "subrace": 20,
    "gender": 2,
    "height": 81,
    "eye_color": 26,
    "hair_color": 17,
    "skin_color": 30,
    "handedness": 2,
    "strength": 7,
    "force": 4,
    "sustain": 2,
    "tolerance": 1,
    "dexterity": 15,
    "speed": 6,
    "precision": 6,
    "reaction": 3,
    "intelligence": 11,
    "memory": 5,
    "processing": 1,
    "reasoning": 5,
    "constitution": 13,
    "healing": 6,
    "fortitude": 6,
    "vitality": 1,
    "luck": 10,
    "accessories": 0,
    "last_updated": 1657904116,
    "meta": {
      "sprite": 8381,
      "card": 8381,
      "canon": "",
      "rumor": ""
    }
  }
}