{
  "status_label": "IPCDB_SUCCESS",
  "responce": {
    "id": 8996,
    "token_id": 8443,
    "name": "Lucky",
    "attribute_seed": "0x082f91c107cdf9811e80ece05977335b11615449a3c99e265c00cde185343c1a",
    "dna": "0x5621fa9f63a135c4cca34deabc903eb059c77ab1be680bb66ad8c7f00c12fab2",
    "birth": 1657069315,
    "price": "500000",
    "gold": 0,
    "xp": 0,
    "owner": "0x27402Ee37441492aeD8CBEdAB7297c609B0167ae",
    "race": 2,
    "subrace": 8,
    "gender": 2,
    "height": 70,
    "eye_color": 19,
    "hair_color": 32,
    "skin_color": 8,
    "handedness": 2,
    "strength": 7,
    "force": 1,
    "sustain": 2,
    "tolerance": 4,
    "dexterity": 11,
    "speed": 5,
    "precision": 1,
    "reaction": 5,
    "intelligence": 11,
    "memory": 6,
    "processing": 4,
    "reasoning": 1,
    "constitution": 16,
    "healing": 4,
    "fortitude": 6,
    "vitality": 6,
    "luck": 10,
    "accessories": 0,
    "last_updated": 1657904179,
    "meta": {
      "sprite": 8443,
      "card": 8443,
      "canon": "",
      "rumor": ""
    }
  }
}