{
  "status_label": "IPCDB_SUCCESS",
  "responce": {
    "id": 3494,
    "token_id": 9024,
    "name": "Chad",
    "attribute_seed": "0x824015ceb3f1e60050e984fceeef38e1438c3af375a63a5bb923f035953eb66e",
    "dna": "0xde6bb76ef65e0703fd5389cc0fe1b2275510a7cb594542ac3ea9fe1a4eb1cdc7",
    "birth": 1657069792,
    "price": "100000000",
    "gold": 0,
    "xp": 0,
    "owner": "0x937cbBa652c5Bac4B3AeaF1E2805E02afA78Fd94",
    "race": 4,
    "subrace": 21,
    "gender": 2,
    "height": 79,
    "eye_color": 26,
    "hair_color": 15,
    "skin_color": 19,
    "handedness": 2,
    "strength": 7,
    "force": 4,
    "sustain": 2,
    "tolerance": 1,
    "dexterity": 16,
    "speed": 5,
    "precision": 5,
    "reaction": 6,
    "intelligence": 9,
    "memory": 6,
    "processing": 1,
    "reasoning": 2,
    "constitution": 16,
    "healing": 6,
    "fortitude": 4,
    "vitality": 6,
    "luck": 9,
    "accessories": 0,
    "last_updated": 1657904885,
    "meta": {
      "sprite": 9024,
      "card": 9024,
      "canon": "",
      "rumor": ""
    }
  }
}