{
  "status_label": "IPCDB_SUCCESS",
  "responce": {
    "id": 10034,
    "token_id": 9700,
    "name": "stevethepirate",
    "attribute_seed": "0xdc04295493162b6fb8c1203da708c309a16062229fa09f6d4a2d7a749c69078e",
    "dna": "0x602a422e8f5598fafca824cd01a6f669c4c97fc1cc3a918c9a8c9cdb4000814a",
    "birth": 1657070153,
    "price": "100000000",
    "gold": 0,
    "xp": 0,
    "owner": "0x5cE9aD759E41BF1b3dFC1a41Db940A90d7a43460",
    "race": 2,
    "subrace": 8,
    "gender": 1,
    "height": 63,
    "eye_color": 19,
    "hair_color": 11,
    "skin_color": 7,
    "handedness": 2,
    "strength": 8,
    "force": 6,
    "sustain": 1,
    "tolerance": 1,
    "dexterity": 7,
    "speed": 2,
    "precision": 4,
    "reaction": 1,
    "intelligence": 10,
    "memory": 2,
    "processing": 3,
    "reasoning": 5,
    "constitution": 8,
    "healing": 5,
    "fortitude": 1,
    "vitality": 2,
    "luck": 13,
    "accessories": 0,
    "last_updated": 1657905558,
    "meta": {
      "sprite": 9700,
      "card": 9700,
      "canon": "",
      "rumor": ""
    }
  }
}