{
  "status_label": "IPCDB_SUCCESS",
  "responce": {
    "id": 10352,
    "token_id": 10037,
    "name": "dominique",
    "attribute_seed": "0xfa7541786a9b5c5e62002b5d9c8d7604373b2a972332068cfaf7f0a0ef6e0757",
    "dna": "0x3b4274041777bfc1adf5515cc8d2e02cf8489d1fd936f05d8458f8084cbdfbca",
    "birth": 1657070262,
    "price": "100000000",
    "gold": 0,
    "xp": 0,
    "owner": "0x4dbF1CAB4594345eD00577329FcFD52eEBF47D3A",
    "race": 2,
    "subrace": 8,
    "gender": 2,
    "height": 64,
    "eye_color": 19,
    "hair_color": 11,
    "skin_color": 7,
    "handedness": 1,
    "strength": 11,
    "force": 6,
    "sustain": 3,
    "tolerance": 2,
    "dexterity": 10,
    "speed": 3,
    "precision": 3,
    "reaction": 4,
    "intelligence": 9,
    "memory": 3,
    "processing": 3,
    "reasoning": 3,
    "constitution": 6,
    "healing": 1,
    "fortitude": 2,
    "vitality": 3,
    "luck": 12,
    "accessories": 0,
    "last_updated": 1657906012,
    "meta": {
      "sprite": 10037,
      "card": 10037,
      "canon": "",
      "rumor": ""
    }
  }
}