{
  "status_label": "IPCDB_SUCCESS",
  "responce": {
    "id": 3705,
    "token_id": 10502,
    "name": "God10",
    "attribute_seed": "0x12693354741223dc7ca994db0a41ede9d77dbe7ff19614c3c8a935c95751d37b",
    "dna": "0xed4fee690e05bc032b40fb4e63b35ee529f41f2bb52435ef94ffa48e0daade57",
    "birth": 1657071018,
    "price": "100000000",
    "gold": 0,
    "xp": 0,
    "owner": "0x4F4b5D02E50e2224258a10354FA6Ec054b4Fb939",
    "race": 4,
    "subrace": 20,
    "gender": 2,
    "height": 79,
    "eye_color": 26,
    "hair_color": 17,
    "skin_color": 7,
    "handedness": 1,
    "strength": 6,
    "force": 1,
    "sustain": 3,
    "tolerance": 2,
    "dexterity": 6,
    "speed": 2,
    "precision": 3,
    "reaction": 1,
    "intelligence": 10,
    "memory": 1,
    "processing": 6,
    "reasoning": 3,
    "constitution": 14,
    "healing": 4,
    "fortitude": 4,
    "vitality": 6,
    "luck": 12,
    "accessories": 0,
    "last_updated": 1657906473,
    "meta": {
      "sprite": 10502,
      "card": 10502,
      "canon": "",
      "rumor": ""
    }
  }
}