{
  "status_label": "IPCDB_SUCCESS",
  "responce": {
    "id": 10925,
    "token_id": 10821,
    "name": "whatyouknowaboutdeez",
    "attribute_seed": "0xcc713b6df44ed6d3ed4cd9f98df1cc8fc29fd5beb9121caade4da99891a2707b",
    "dna": "0x883138ee809cee813c3f81a996e2813379a2f785d8d2862c5ab7dc804a850398",
    "birth": 1657072288,
    "price": "100000000",
    "gold": 0,
    "xp": 0,
    "owner": "0x67161DFE25Fc3eb99A1a13a3C4f3C6A0e22a80a9",
    "race": 2,
    "subrace": 8,
    "gender": 1,
    "height": 70,
    "eye_color": 3,
    "hair_color": 15,
    "skin_color": 8,
    "handedness": 2,
    "strength": 10,
    "force": 5,
    "sustain": 3,
    "tolerance": 2,
    "dexterity": 11,
    "speed": 3,
    "precision": 6,
    "reaction": 2,
    "intelligence": 17,
    "memory": 6,
    "processing": 5,
    "reasoning": 6,
    "constitution": 14,
    "healing": 2,
    "fortitude": 6,
    "vitality": 6,
    "luck": 8,
    "accessories": 0,
    "last_updated": 1657906790,
    "meta": {
      "sprite": 10821,
      "card": 10821,
      "canon": "",
      "rumor": ""
    }
  }
}