{
  "status_label": "IPCDB_SUCCESS",
  "responce": {
    "id": 9039,
    "token_id": 10846,
    "name": "orc",
    "attribute_seed": "0x3fcbb031c1a074fca5ce03425cc98224603d7a13b57842edb7b55df664f7e15e",
    "dna": "0x6eb4e969f64fc0e23292931fdab4b370e232b1498469e984dd358442c27d465f",
    "birth": 1657072567,
    "price": "10000",
    "gold": 0,
    "xp": 0,
    "owner": "0x82E63A0FA475E1F11bad26dAea4F0872ad89C065",
    "race": 2,
    "subrace": 10,
    "gender": 2,
    "height": 69,
    "eye_color": 12,
    "hair_color": 17,
    "skin_color": 8,
    "handedness": 2,
    "strength": 12,
    "force": 2,
    "sustain": 5,
    "tolerance": 5,
    "dexterity": 11,
    "speed": 2,
    "precision": 5,
    "reaction": 4,
    "intelligence": 13,
    "memory": 3,
    "processing": 6,
    "reasoning": 4,
    "constitution": 8,
    "healing": 5,
    "fortitude": 1,
    "vitality": 2,
    "luck": 10,
    "accessories": 0,
    "last_updated": 1657906814,
    "meta": {
      "sprite": 10846,
      "card": 10846,
      "canon": "",
      "rumor": ""
    }
  }
}