{
  "status_label": "IPCDB_SUCCESS",
  "responce": {
    "id": 11879,
    "token_id": 11890,
    "name": "NFT",
    "attribute_seed": "0xe559aeb603e957a0d8009f02f785108dae724e2072d8c120823b9cdd7e729782",
    "dna": "0x37e0d9386c44dff583e48c6b5f3d6678dd134d6d790dfaac1b38232ba9aee7ca",
    "birth": 1657144004,
    "price": "100000",
    "gold": 0,
    "xp": 0,
    "owner": "0xE71ce0644a77252F9e0Bf3Da84bC13Fa6072AB4C",
    "race": 1,
    "subrace": 4,
    "gender": 2,
    "height": 74,
    "eye_color": 26,
    "hair_color": 12,
    "skin_color": 10,
    "handedness": 2,
    "strength": 14,
    "force": 6,
    "sustain": 3,
    "tolerance": 5,
    "dexterity": 12,
    "speed": 5,
    "precision": 1,
    "reaction": 6,
    "intelligence": 13,
    "memory": 3,
    "processing": 4,
    "reasoning": 6,
    "constitution": 6,
    "healing": 1,
    "fortitude": 4,
    "vitality": 1,
    "luck": 10,
    "accessories": 0,
    "last_updated": 1657907852,
    "meta": {
      "sprite": 11890,
      "card": 11890,
      "canon": "",
      "rumor": ""
    }
  }
}