{
  "status_label": "IPCDB_SUCCESS",
  "responce": {
    "id": 11977,
    "token_id": 11989,
    "name": "suck",
    "attribute_seed": "0x3a1786f001ecece573c1f8e460c1417ff5971333fbfe3ef955b108d8ba2ef73a",
    "dna": "0x4f1a5d9869c0da8437f37ba3f7219081d94c65ba25e8545b8253355f9ac2030e",
    "birth": 1657144026,
    "price": "100000000",
    "gold": 0,
    "xp": 0,
    "owner": "0x0eE01Fd0BDb6B449CF343EcAFA7116BE49B5286A",
    "race": 2,
    "subrace": 7,
    "gender": 1,
    "height": 66,
    "eye_color": 15,
    "hair_color": 17,
    "skin_color": 0,
    "handedness": 2,
    "strength": 7,
    "force": 2,
    "sustain": 1,
    "tolerance": 4,
    "dexterity": 13,
    "speed": 6,
    "precision": 1,
    "reaction": 6,
    "intelligence": 15,
    "memory": 6,
    "processing": 6,
    "reasoning": 3,
    "constitution": 17,
    "healing": 5,
    "fortitude": 6,
    "vitality": 6,
    "luck": 8,
    "accessories": 0,
    "last_updated": 1657907950,
    "meta": {
      "sprite": 11989,
      "card": 11989,
      "canon": "",
      "rumor": ""
    }
  }
}