{
  "status_label": "IPCDB_SUCCESS",
  "responce": {
    "id": 890,
    "token_id": 890,
    "name": "Katsumi",
    "attribute_seed": "0x62f253acfe7125461701e0de8ce3f5831a9d36808f358675482fdfe455105816",
    "dna": "0x3da82cb6fc71d30def17a99fd1549e1bbf7c9290e948f7d62dcd49ee0820e0b3",
    "birth": 1539294020,
    "price": "1000000000",
    "gold": 0,
    "xp": 0,
    "owner": "0x178a38b3D7FEf32f62Dd3b39a67d50ed335C87c3",
    "race": 2,
    "subrace": 10,
    "gender": 1,
    "height": 67,
    "eye_color": 3,
    "hair_color": 17,
    "skin_color": 10,
    "handedness": 2,
    "strength": 11,
    "force": 3,
    "sustain": 6,
    "tolerance": 2,
    "dexterity": 14,
    "speed": 5,
    "precision": 6,
    "reaction": 3,
    "intelligence": 4,
    "memory": 1,
    "processing": 2,
    "reasoning": 1,
    "constitution": 13,
    "healing": 1,
    "fortitude": 6,
    "vitality": 6,
    "luck": 11,
    "accessories": 0,
    "last_updated": 1657895832,
    "meta": {
      "sprite": "890",
      "card": 890,
      "canon": "",
      "rumor": ""
    }
  }
}