{
  "status_label": "IPCDB_SUCCESS",
  "responce": {
    "id": 1105,
    "token_id": 1105,
    "name": "Diocleziano Lepore",
    "attribute_seed": "0x73c8d635765351d65633f0d24450037ec1e418522ee264e5b0290daea5cd3eff",
    "dna": "0xd9cd29259c338a0c645b7fa37a72609cfbb6f71cd476f7ef093107cc06fe8d31",
    "birth": 1539639442,
    "price": "100000000",
    "gold": 0,
    "xp": 0,
    "owner": "0xEC26e534b67CE28bE123fD72fbbf3f0fF89a5De2",
    "race": 4,
    "subrace": 21,
    "gender": 1,
    "height": 72,
    "eye_color": 26,
    "hair_color": 12,
    "skin_color": 23,
    "handedness": 2,
    "strength": 14,
    "force": 3,
    "sustain": 5,
    "tolerance": 6,
    "dexterity": 7,
    "speed": 2,
    "precision": 3,
    "reaction": 2,
    "intelligence": 11,
    "memory": 2,
    "processing": 6,
    "reasoning": 3,
    "constitution": 13,
    "healing": 2,
    "fortitude": 6,
    "vitality": 5,
    "luck": 10,
    "accessories": 0,
    "last_updated": 1657896171,
    "meta": {
      "sprite": "1105",
      "card": 1105,
      "canon": "",
      "rumor": ""
    }
  }
}