{
  "status_label": "IPCDB_SUCCESS",
  "responce": {
    "id": 1182,
    "token_id": 1182,
    "name": "Joshua Nicholson",
    "attribute_seed": "0x1d99e0677ad6a87136766a2ddfe7d1be09ec0879a8dc8637a51ecccc55b8475d",
    "dna": "0x5c6595c16b59edf0cf03c478b60d45fde159e91af6022df95de9ae60fefb1468",
    "birth": 1539649057,
    "price": "100000000",
    "gold": 0,
    "xp": 0,
    "owner": "0x9BDEd86154dA7255e3bE244A842FAd6aee0EeDb0",
    "race": 2,
    "subrace": 8,
    "gender": 2,
    "height": 72,
    "eye_color": 19,
    "hair_color": 15,
    "skin_color": 7,
    "handedness": 2,
    "strength": 11,
    "force": 1,
    "sustain": 4,
    "tolerance": 6,
    "dexterity": 12,
    "speed": 3,
    "precision": 3,
    "reaction": 6,
    "intelligence": 9,
    "memory": 4,
    "processing": 3,
    "reasoning": 2,
    "constitution": 8,
    "healing": 3,
    "fortitude": 3,
    "vitality": 2,
    "luck": 11,
    "accessories": 0,
    "last_updated": 1657896246,
    "meta": {
      "sprite": "1182",
      "card": 1182,
      "canon": "",
      "rumor": ""
    }
  }
}