{
  "status_label": "IPCDB_SUCCESS",
  "responce": {
    "id": 2884,
    "token_id": 2918,
    "name": "Getruggedordietrying",
    "attribute_seed": "0xc52705f6324849038311016c1f4818bbc122d87397f6741824ae6a59c139c3df",
    "dna": "0x120ce6b0e3bf75359f6252df87973158e21dbe1f7ad79b84beace9991fc9628e",
    "birth": 1657060602,
    "price": "100000000",
    "gold": 0,
    "xp": 0,
    "owner": "0xAd9F11D1DD6D202243473A0CdaE606308aB243B4",
    "race": 1,
    "subrace": 1,
    "gender": 2,
    "height": 76,
    "eye_color": 18,
    "hair_color": 4,
    "skin_color": 2,
    "handedness": 2,
    "strength": 7,
    "force": 5,
    "sustain": 1,
    "tolerance": 1,
    "dexterity": 10,
    "speed": 6,
    "precision": 2,
    "reaction": 2,
    "intelligence": 7,
    "memory": 2,
    "processing": 1,
    "reasoning": 4,
    "constitution": 5,
    "healing": 1,
    "fortitude": 1,
    "vitality": 3,
    "luck": 14,
    "accessories": 0,
    "last_updated": 1657898326,
    "meta": {
      "sprite": 2918,
      "card": 2918,
      "canon": "",
      "rumor": ""
    }
  }
}