{
  "status_label": "IPCDB_SUCCESS",
  "responce": {
    "id": 3016,
    "token_id": 3715,
    "name": "littledegen",
    "attribute_seed": "0x7da564b6619c7cde0562f8ec1ef9da990031dcbc84f746665534f329d7b7d51a",
    "dna": "0x013ad75e840b4707a66ba0e4edbc2f016ece6f3efbe40d8d389d1d372d969d49",
    "birth": 1657066652,
    "price": "100000000",
    "gold": 0,
    "xp": 0,
    "owner": "0xd0Adc5d079Cc486b58F1B9A28B973355C4ec9e6f",
    "race": 1,
    "subrace": 2,
    "gender": 2,
    "height": 75,
    "eye_color": 3,
    "hair_color": 11,
    "skin_color": 7,
    "handedness": 2,
    "strength": 10,
    "force": 3,
    "sustain": 4,
    "tolerance": 3,
    "dexterity": 12,
    "speed": 5,
    "precision": 3,
    "reaction": 4,
    "intelligence": 10,
    "memory": 3,
    "processing": 6,
    "reasoning": 1,
    "constitution": 15,
    "healing": 3,
    "fortitude": 6,
    "vitality": 6,
    "luck": 10,
    "accessories": 0,
    "last_updated": 1657899117,
    "meta": {
      "sprite": 3715,
      "card": 3715,
      "canon": "",
      "rumor": ""
    }
  }
}