{
  "status_label": "IPCDB_SUCCESS",
  "responce": {
    "id": 5004,
    "token_id": 4086,
    "name": "balls",
    "attribute_seed": "0xa4ba1bdb98e623b10195b64c6fd75840067eb7f5c06825f1311c084b8bb0db6a",
    "dna": "0x5e82e4767eccc620967a9c38d55b5064ce30392dde234027d754e485d084e7c0",
    "birth": 1657067336,
    "price": "100000000",
    "gold": 0,
    "xp": 0,
    "owner": "0x4836AE11037f696693C2916834754FA6C2ecc27d",
    "race": 2,
    "subrace": 9,
    "gender": 2,
    "height": 69,
    "eye_color": 27,
    "hair_color": 17,
    "skin_color": 10,
    "handedness": 2,
    "strength": 10,
    "force": 4,
    "sustain": 5,
    "tolerance": 1,
    "dexterity": 16,
    "speed": 6,
    "precision": 4,
    "reaction": 6,
    "intelligence": 7,
    "memory": 1,
    "processing": 5,
    "reasoning": 1,
    "constitution": 11,
    "healing": 4,
    "fortitude": 5,
    "vitality": 2,
    "luck": 10,
    "accessories": 0,
    "last_updated": 1657899484,
    "meta": {
      "sprite": 4086,
      "card": 4086,
      "canon": "",
      "rumor": ""
    }
  }
}