{
  "status_label": "IPCDB_SUCCESS",
  "responce": {
    "id": 6232,
    "token_id": 5421,
    "name": "Lucky",
    "attribute_seed": "0x0db967302f888588367347e384d6bb03c3cefed6bc1f582600fa825eae354fc9",
    "dna": "0xdd7204536e41b322f8581f335d9c6ff3ff981a064d623766affd20fd19fb4e91",
    "birth": 1657067948,
    "price": "500000",
    "gold": 0,
    "xp": 0,
    "owner": "0x061f7DA2187f9B8f5F02171C799E7428cDC5739f",
    "race": 4,
    "subrace": 21,
    "gender": 1,
    "height": 74,
    "eye_color": 26,
    "hair_color": 17,
    "skin_color": 23,
    "handedness": 2,
    "strength": 9,
    "force": 1,
    "sustain": 5,
    "tolerance": 3,
    "dexterity": 8,
    "speed": 2,
    "precision": 2,
    "reaction": 4,
    "intelligence": 10,
    "memory": 4,
    "processing": 4,
    "reasoning": 2,
    "constitution": 11,
    "healing": 3,
    "fortitude": 2,
    "vitality": 6,
    "luck": 12,
    "accessories": 0,
    "last_updated": 1657900940,
    "meta": {
      "sprite": 5421,
      "card": 5421,
      "canon": "",
      "rumor": ""
    }
  }
}