{
  "status_label": "IPCDB_SUCCESS",
  "responce": {
    "id": 6303,
    "token_id": 5499,
    "name": "Lucky",
    "attribute_seed": "0xe1d49fa5fe9b35b148c439c89b7f3e5d32106596ebcb82540b0ec9e277d6c577",
    "dna": "0x47e24de0590091f8fa604fd8ab0e8672c7ae78f832bdd172e3b0516aa860741d",
    "birth": 1657068009,
    "price": "500000",
    "gold": 0,
    "xp": 0,
    "owner": "0xD4429b12933575a8E3744BA402c756eAF5120CE2",
    "race": 2,
    "subrace": 11,
    "gender": 1,
    "height": 69,
    "eye_color": 17,
    "hair_color": 16,
    "skin_color": 11,
    "handedness": 2,
    "strength": 15,
    "force": 6,
    "sustain": 5,
    "tolerance": 4,
    "dexterity": 14,
    "speed": 4,
    "precision": 6,
    "reaction": 4,
    "intelligence": 9,
    "memory": 2,
    "processing": 5,
    "reasoning": 2,
    "constitution": 12,
    "healing": 5,
    "fortitude": 2,
    "vitality": 5,
    "luck": 9,
    "accessories": 0,
    "last_updated": 1657901018,
    "meta": {
      "sprite": 5499,
      "card": 5499,
      "canon": "",
      "rumor": ""
    }
  }
}