{
  "status_label": "IPCDB_SUCCESS",
  "responce": {
    "id": 6388,
    "token_id": 5596,
    "name": "",
    "attribute_seed": "0x102103c19a838e824f2ba66751db78552698901fa9ce52e1965c01f1d8ca3129",
    "dna": "0xaec291924956637d80686560cc49698a34d491a2c1d63a9035cd31d2837659a2",
    "birth": 1657068053,
    "price": "100000000",
    "gold": 0,
    "xp": 0,
    "owner": "0xa0041A1685171b8a426A93CFcfF7A9bf59FD51F9",
    "race": 3,
    "subrace": 15,
    "gender": 2,
    "height": 51,
    "eye_color": 27,
    "hair_color": 12,
    "skin_color": 11,
    "handedness": 2,
    "strength": 3,
    "force": 1,
    "sustain": 1,
    "tolerance": 1,
    "dexterity": 13,
    "speed": 5,
    "precision": 4,
    "reaction": 4,
    "intelligence": 10,
    "memory": 4,
    "processing": 4,
    "reasoning": 2,
    "constitution": 9,
    "healing": 2,
    "fortitude": 4,
    "vitality": 3,
    "luck": 13,
    "accessories": 0,
    "last_updated": 1657901115,
    "meta": {
      "sprite": 5596,
      "card": 5596,
      "canon": "",
      "rumor": ""
    }
  }
}