{
  "status_label": "IPCDB_SUCCESS",
  "responce": {
    "id": 6976,
    "token_id": 6251,
    "name": "suck",
    "attribute_seed": "0xbedb956e3ca5d966f19aba1110ed2117ec47bfbe67b1c81bdf2d6ee3b9da6f1b",
    "dna": "0x9fe9940cac04d26d6d71a1c69e67ac7849cf131e6cef5bbfbd891b3dbe84e77b",
    "birth": 1657068426,
    "price": "100000000",
    "gold": 0,
    "xp": 0,
    "owner": "0xc636A5c78860Ca9Dd12457ca7af2f5d6dcb279f4",
    "race": 3,
    "subrace": 16,
    "gender": 2,
    "height": 48,
    "eye_color": 12,
    "hair_color": 17,
    "skin_color": 16,
    "handedness": 2,
    "strength": 15,
    "force": 5,
    "sustain": 6,
    "tolerance": 4,
    "dexterity": 9,
    "speed": 3,
    "precision": 2,
    "reaction": 4,
    "intelligence": 15,
    "memory": 6,
    "processing": 3,
    "reasoning": 6,
    "constitution": 10,
    "healing": 4,
    "fortitude": 5,
    "vitality": 1,
    "luck": 9,
    "accessories": 0,
    "last_updated": 1657901887,
    "meta": {
      "sprite": 6251,
      "card": 6251,
      "canon": "",
      "rumor": ""
    }
  }
}