{
  "status_label": "IPCDB_SUCCESS",
  "responce": {
    "id": 7258,
    "token_id": 6533,
    "name": "Lucky",
    "attribute_seed": "0x642f007ed0db92f6be3d0a70c59da3594426c5ff0dbb240c86f14cb3cff04526",
    "dna": "0xd01a359bba742b8fc602365981d533a8b5f8edf66e5b56c381d15ee6b3761388",
    "birth": 1657068560,
    "price": "500000",
    "gold": 0,
    "xp": 0,
    "owner": "0xB7628368af247D151De01f014784D2C499d234de",
    "race": 4,
    "subrace": 19,
    "gender": 1,
    "height": 76,
    "eye_color": 12,
    "hair_color": 0,
    "skin_color": 16,
    "handedness": 2,
    "strength": 6,
    "force": 3,
    "sustain": 2,
    "tolerance": 1,
    "dexterity": 14,
    "speed": 3,
    "precision": 5,
    "reaction": 6,
    "intelligence": 15,
    "memory": 4,
    "processing": 6,
    "reasoning": 5,
    "constitution": 6,
    "healing": 2,
    "fortitude": 1,
    "vitality": 3,
    "luck": 11,
    "accessories": 0,
    "last_updated": 1657902166,
    "meta": {
      "sprite": 6533,
      "card": 6533,
      "canon": "",
      "rumor": ""
    }
  }
}