{
  "status_label": "IPCDB_SUCCESS",
  "responce": {
    "id": 8557,
    "token_id": 7935,
    "name": "Lucky",
    "attribute_seed": "0x72585c0936d1054c820952c135fd312867c399ec5f414e55599d498fce7259e3",
    "dna": "0xa636cbc4b27c17122ed84f5f1deaaa17b6001898ea8213a3d5a4fea8b323a5ce",
    "birth": 1657069004,
    "price": "500000",
    "gold": 0,
    "xp": 0,
    "owner": "0xd4e4FB798387FAd486DB864EE4fe033D0cA10800",
    "race": 3,
    "subrace": 14,
    "gender": 2,
    "height": 52,
    "eye_color": 3,
    "hair_color": 12,
    "skin_color": 8,
    "handedness": 2,
    "strength": 9,
    "force": 3,
    "sustain": 3,
    "tolerance": 3,
    "dexterity": 8,
    "speed": 1,
    "precision": 2,
    "reaction": 5,
    "intelligence": 7,
    "memory": 1,
    "processing": 2,
    "reasoning": 4,
    "constitution": 8,
    "healing": 1,
    "fortitude": 2,
    "vitality": 5,
    "luck": 13,
    "accessories": 0,
    "last_updated": 1657903674,
    "meta": {
      "sprite": 7935,
      "card": 7935,
      "canon": "",
      "rumor": ""
    }
  }
}