{
  "status_label": "IPCDB_SUCCESS",
  "responce": {
    "id": 8984,
    "token_id": 8431,
    "name": "Lucky",
    "attribute_seed": "0x6a4d027e9f3c484e7c9db3901af0796f5794d85904fb03565a410cdb2990cb98",
    "dna": "0x091798d6cfdb19b122ab7d0f1197e0003f62b45bcc66172fd35397228e78b75e",
    "birth": 1657069315,
    "price": "500000",
    "gold": 0,
    "xp": 0,
    "owner": "0xB365Bf238a4d613c1C222ff1838D7236996864cF",
    "race": 1,
    "subrace": 1,
    "gender": 2,
    "height": 76,
    "eye_color": 3,
    "hair_color": 3,
    "skin_color": 2,
    "handedness": 2,
    "strength": 6,
    "force": 3,
    "sustain": 2,
    "tolerance": 1,
    "dexterity": 9,
    "speed": 3,
    "precision": 4,
    "reaction": 2,
    "intelligence": 7,
    "memory": 2,
    "processing": 2,
    "reasoning": 3,
    "constitution": 13,
    "healing": 4,
    "fortitude": 5,
    "vitality": 4,
    "luck": 13,
    "accessories": 0,
    "last_updated": 1657904167,
    "meta": {
      "sprite": 8431,
      "card": 8431,
      "canon": "",
      "rumor": ""
    }
  }
}