{
  "status_label": "IPCDB_SUCCESS",
  "responce": {
    "id": 9924,
    "token_id": 9576,
    "name": "stevethepirate",
    "attribute_seed": "0x1629c5dc1d54902dde5655c16d07708d667887d3152bb2f4854d4340de08ca7d",
    "dna": "0x8ad95ded41b4d4ec20b6dfe05851494a5ef2b22c29c7a6b118094a6f419c0b5d",
    "birth": 1657070109,
    "price": "100000000",
    "gold": 0,
    "xp": 0,
    "owner": "0xEce41CC3342b5e5720A6d891a1134449c2Fb28C3",
    "race": 3,
    "subrace": 16,
    "gender": 2,
    "height": 53,
    "eye_color": 17,
    "hair_color": 17,
    "skin_color": 13,
    "handedness": 2,
    "strength": 7,
    "force": 1,
    "sustain": 1,
    "tolerance": 5,
    "dexterity": 9,
    "speed": 6,
    "precision": 1,
    "reaction": 2,
    "intelligence": 12,
    "memory": 4,
    "processing": 2,
    "reasoning": 6,
    "constitution": 10,
    "healing": 3,
    "fortitude": 2,
    "vitality": 5,
    "luck": 12,
    "accessories": 0,
    "last_updated": 1657905435,
    "meta": {
      "sprite": 9576,
      "card": 9576,
      "canon": "",
      "rumor": ""
    }
  }
}