{
  "status_label": "IPCDB_SUCCESS",
  "responce": {
    "id": 8536,
    "token_id": 10431,
    "name": "cheese",
    "attribute_seed": "0x4b018f4057fa8064f3e89be5294476a2807c2edc30c5123a8d388a7e5144b595",
    "dna": "0xb1d8acd113f522551edb52fc69d2ab6d924db7b1846a7584c096fa53a19bca4d",
    "birth": 1657070683,
    "price": "100000000",
    "gold": 0,
    "xp": 0,
    "owner": "0x131aA683891C534828aE98c4f743ABa334769371",
    "race": 3,
    "subrace": 16,
    "gender": 2,
    "height": 52,
    "eye_color": 27,
    "hair_color": 12,
    "skin_color": 13,
    "handedness": 1,
    "strength": 7,
    "force": 2,
    "sustain": 1,
    "tolerance": 4,
    "dexterity": 11,
    "speed": 2,
    "precision": 3,
    "reaction": 6,
    "intelligence": 13,
    "memory": 4,
    "processing": 3,
    "reasoning": 6,
    "constitution": 16,
    "healing": 6,
    "fortitude": 4,
    "vitality": 6,
    "luck": 10,
    "accessories": 0,
    "last_updated": 1657906403,
    "meta": {
      "sprite": 10431,
      "card": 10431,
      "canon": "",
      "rumor": ""
    }
  }
}